LICENSE
README.md
pyproject.toml
setup.cfg
setup.py
ph4_monitlib.egg-info/PKG-INFO
ph4_monitlib.egg-info/SOURCES.txt
ph4_monitlib.egg-info/dependency_links.txt
ph4_monitlib.egg-info/requires.txt
ph4_monitlib.egg-info/top_level.txt
ph4monitlib/__init__.py
ph4monitlib/comm.py
ph4monitlib/flaky.py
ph4monitlib/mute.py
ph4monitlib/net.py
ph4monitlib/notif.py
ph4monitlib/rate_limit.py
ph4monitlib/tbot.py
ph4monitlib/utils.py
ph4monitlib/worker.py
tests/test_flaky.py
tests/test_main.py
tests/test_mute.py
tests/test_rate_limiter.py